[
    {
        "username": "kajol",
        "password": "12345678",
        "nidno": "1111111",
        "address": "fdsgsfsdfgsdfgfsgfsdghfsdhh",
        "phone": "01923847456547",
        "email": "kajol.99bd@gmail.com"
    },
    {
        "username": "kajol",
        "password": "12345678",
        "nidno": "1111111",
        "address": "fdsgsfsdfgsdfgfsgfsdghfsdhh",
        "phone": "01923847456547",
        "email": "kajol.99bd@gmail.com"
    },
    {
        "username": "Eshrat jahan",
        "password": "87654321",
        "nidno": "4231111",
        "address": "fdsghsfdhfghgfhjgfhjgjfgj",
        "phone": "01923847456547",
        "email": "eshrat@gmail.com"
    }
]